milcapy/__init__.py
milcapy/analysis/__init__.py
milcapy/analysis/linear_static.py
milcapy/analysis/manager.py
milcapy/core/__init__.py
milcapy/core/node.py
milcapy/core/results.py
milcapy/elements/CST.py
milcapy/elements/MQ6.py
milcapy/elements/MQ6I.py
milcapy/elements/MQ6IMod.py
milcapy/elements/__init__.py
milcapy/elements/member.py
milcapy/elements/quad4.py
milcapy/elements/quad8.py
milcapy/elements/truss.py
milcapy/loads/__init__.py
milcapy/loads/load.py
milcapy/loads/load_pattern.py
milcapy/material/__init__.py
milcapy/material/material.py
milcapy/model/__init__.py
milcapy/model/model.py
milcapy/plotter/UIdisplay.py
milcapy/plotter/__init__.py
milcapy/plotter/load.py
milcapy/plotter/options.py
milcapy/plotter/plot_model.py
milcapy/plotter/plotter.py
milcapy/plotter/plotter_values.py
milcapy/plotter/suports.py
milcapy/plotter/utils.py
milcapy/plotter/widgets.py
milcapy/plotter/assets/milca.ico
milcapy/postprocess/CST_pp.py
milcapy/postprocess/__init__.py
milcapy/postprocess/membranebQ6.py
milcapy/postprocess/post_processing.py
milcapy/postprocess/segment_member.py
milcapy/report/__init__.py
milcapy/report/report.py
milcapy/section/__init__.py
milcapy/section/section.py
milcapy/utils/__init__.py
milcapy/utils/element.py
milcapy/utils/geometry.py
milcapy/utils/types.py
milcapy-0.2.6.dist-info/METADATA
milcapy-0.2.6.dist-info/WHEEL
milcapy-0.2.6.dist-info/top_level.txt
milcapy-0.2.6.dist-info/RECORD
