Metadata-Version: 2.4
Name: milcapy
Version: 0.2.6
Summary: Librería para el análisis de estructuras 2D (Frame, Truss, CST, Membrana: Q4, Q8, Q6, Q6i).
Author-email: Amilcar Machacca Mayo <200190@unsaac.edu.pe>
License: MIT
Project-URL: Homepage, https://github.com/Milca-py/MilcaStructures
Classifier: Programming Language :: Python :: 3
Classifier: License :: OSI Approved :: MIT License
Classifier: Operating System :: OS Independent
Requires-Python: >=3.10
